amranjupyterlab-0.0.0.data/data/etc/jupyter/jupyter_notebook_config.d/jupyterlab.json
amranjupyterlab-0.0.0.data/data/share/jupyter/lab/schemas/@jupyterlab/application-extension/main.json
amranjupyterlab-0.0.0.data/data/share/jupyter/lab/schemas/@jupyterlab/application-extension/package.json.orig
amranjupyterlab-0.0.0.data/data/share/jupyter/lab/schemas/@jupyterlab/application-extension/sidebar.json
amranjupyterlab-0.0.0.data/data/share/jupyter/lab/schemas/@jupyterlab/apputils-extension/package.json.orig
amranjupyterlab-0.0.0.data/data/share/jupyter/lab/schemas/@jupyterlab/apputils-extension/palette.json
amranjupyterlab-0.0.0.data/data/share/jupyter/lab/schemas/@jupyterlab/apputils-extension/print.json
amranjupyterlab-0.0.0.data/data/share/jupyter/lab/schemas/@jupyterlab/apputils-extension/themes.json
amranjupyterlab-0.0.0.data/data/share/jupyter/lab/schemas/@jupyterlab/codemirror-extension/commands.json
amranjupyterlab-0.0.0.data/data/share/jupyter/lab/schemas/@jupyterlab/codemirror-extension/package.json.orig
amranjupyterlab-0.0.0.data/data/share/jupyter/lab/schemas/@jupyterlab/completer-extension/consoles.json
amranjupyterlab-0.0.0.data/data/share/jupyter/lab/schemas/@jupyterlab/completer-extension/files.json
amranjupyterlab-0.0.0.data/data/share/jupyter/lab/schemas/@jupyterlab/completer-extension/notebooks.json
amranjupyterlab-0.0.0.data/data/share/jupyter/lab/schemas/@jupyterlab/completer-extension/package.json.orig
amranjupyterlab-0.0.0.data/data/share/jupyter/lab/schemas/@jupyterlab/console-extension/package.json.orig
amranjupyterlab-0.0.0.data/data/share/jupyter/lab/schemas/@jupyterlab/console-extension/tracker.json
amranjupyterlab-0.0.0.data/data/share/jupyter/lab/schemas/@jupyterlab/docmanager-extension/package.json.orig
amranjupyterlab-0.0.0.data/data/share/jupyter/lab/schemas/@jupyterlab/docmanager-extension/plugin.json
amranjupyterlab-0.0.0.data/data/share/jupyter/lab/schemas/@jupyterlab/documentsearch-extension/package.json.orig
amranjupyterlab-0.0.0.dist-info/LICENSE
amranjupyterlab-0.0.0.dist-info/METADATA
amranjupyterlab-0.0.0.dist-info/WHEEL
amranjupyterlab-0.0.0.dist-info/entry_points.txt
amranjupyterlab-0.0.0.dist-info/top_level.txt
amranjupyterlab-0.0.0.dist-info/RECORD
