Metadata-Version: 2.1
Name: amranjupyterlab
Version: 0.0.0
Summary: The JupyterLab notebook server extension.
Home-page: http://jupyter.org
Author: Jupyter Development Team
Author-email: jupyter@googlegroups.com
License: BSD
Keywords: ipython,jupyter,Web
Platform: Linux
Platform: Mac OS X
Platform: Windows
Classifier: Development Status :: 5 - Production/Stable
Classifier: Intended Audience :: Developers
Classifier: Intended Audience :: System Administrators
Classifier: Intended Audience :: Science/Research
Classifier: License :: OSI Approved :: BSD License
Classifier: Programming Language :: Python
Classifier: Programming Language :: Python :: 3
Classifier: Programming Language :: Python :: 3.5
Classifier: Programming Language :: Python :: 3.6
Classifier: Programming Language :: Python :: 3.7
Requires-Python: >=3.5
Requires-Dist: notebook (>=4.3.1)
Requires-Dist: tornado (!=6.0.0,!=6.0.1,!=6.0.2)
Requires-Dist: jupyterlab-server (<2.0,>=1.1.5)
Requires-Dist: jinja2 (>=2.10)
Provides-Extra: docs
Requires-Dist: jsx-lexer ; extra == 'docs'
Requires-Dist: recommonmark ; extra == 'docs'
Requires-Dist: sphinx ; extra == 'docs'
Requires-Dist: sphinx-rtd-theme ; extra == 'docs'
Requires-Dist: sphinx-copybutton ; extra == 'docs'
Provides-Extra: test
Requires-Dist: pytest ; extra == 'test'
Requires-Dist: pytest-check-links ; extra == 'test'
Requires-Dist: requests ; extra == 'test'
Requires-Dist: wheel ; extra == 'test'
Requires-Dist: virtualenv ; extra == 'test'
